cased_cli/__init__.py
cased_cli/cli.py
cased_cli/.vscode/settings.json
cased_cli/commands/__init__.py
cased_cli/commands/build.py
cased_cli/commands/deploy.py
cased_cli/commands/init.py
cased_cli/commands/login.py
cased_cli/commands/resources.py
cased_cli/templates/docker_ec2_template.yaml
cased_cli/templates/non_docker_ec2_template.yaml
cased_cli/utils/api.py
cased_cli/utils/auth.py
cased_cli/utils/config.py
cased_cli/utils/constants.py
cased_cli/utils/exception.py
cased_cli/utils/git.py
cased_cli/utils/progress.py
cased_cli-0.1.0.dist-info/METADATA
cased_cli-0.1.0.dist-info/WHEEL
cased_cli-0.1.0.dist-info/entry_points.txt
cased_cli-0.1.0.dist-info/licenses/LICENSE
cased_cli-0.1.0.dist-info/RECORD
