Metadata-Version: 2.4
Name: cased-cli
Version: 0.1.0
Summary: A CLI tool for managing cloud infrastructure
License-File: LICENSE
Requires-Python: >=3.12
Requires-Dist: ansicon==1.89.0
Requires-Dist: blessed==1.20.0
Requires-Dist: certifi==2024.8.30
Requires-Dist: cfgv==3.4.0
Requires-Dist: charset-normalizer==3.3.2
Requires-Dist: click==8.1.7
Requires-Dist: colorama==0.4.6
Requires-Dist: commonmark==0.9.1
Requires-Dist: distlib==0.3.8
Requires-Dist: editor==1.6.6
Requires-Dist: filelock==3.16.1
Requires-Dist: identify==2.6.1
Requires-Dist: idna==3.10
Requires-Dist: inquirer==3.4.0
Requires-Dist: isort==5.13.2
Requires-Dist: jinja2==3.1.4
Requires-Dist: jinxed==1.3.0
Requires-Dist: markupsafe==2.1.5
Requires-Dist: nodeenv==1.9.1
Requires-Dist: platformdirs==4.3.6
Requires-Dist: pre-commit==3.8.0
Requires-Dist: prompt-toolkit==3.0.36
Requires-Dist: pygments==2.18.0
Requires-Dist: python-dateutil==2.9.0.post0
Requires-Dist: pyyaml==6.0.2
Requires-Dist: questionary==2.0.1
Requires-Dist: readchar==4.2.0
Requires-Dist: requests==2.32.3
Requires-Dist: rich==12.6.0
Requires-Dist: ruff==0.6.8
Requires-Dist: runs==1.2.2
Requires-Dist: six==1.16.0
Requires-Dist: urllib3==2.2.3
Requires-Dist: virtualenv==20.26.6
Requires-Dist: wcwidth==0.2.13
Requires-Dist: xmod==1.8.1
